bulma_widget/__init__.py
bulma_widget/form.py
bulma_widget/tests.py
bulma_widget/widgets.py
bulma_widget/static/bulma_widget/css/bulma-calendar.min.css
bulma_widget/static/bulma_widget/css/bulma.min.css
bulma_widget/static/bulma_widget/js/bulma-calendar.min.js
bulma_widget/templates/bulma_widget/_form_errors.djhtml
bulma_widget/templates/bulma_widget/_messages.djhtml
bulma_widget/templates/bulma_widget/form.djhtml
bulma_widget/templates/bulma_widget/table.djhtml
django_bulma_widget-1.2.dist-info/LICENSE
django_bulma_widget-1.2.dist-info/METADATA
django_bulma_widget-1.2.dist-info/WHEEL
django_bulma_widget-1.2.dist-info/top_level.txt
django_bulma_widget-1.2.dist-info/RECORD
